baumanecbank_common/__init__.py
baumanecbank_common/abstract.py
baumanecbank_common/application.py
baumanecbank_common/application_create.py
baumanecbank_common/filter.py
baumanecbank_common/handlers.py
baumanecbank_common/i18n.py
baumanecbank_common/log.py
baumanecbank_common/postgres.py
baumanecbank_common/qr.py
baumanecbank_common-1.2.1.dist-info/METADATA
baumanecbank_common-1.2.1.dist-info/WHEEL
baumanecbank_common-1.2.1.dist-info/RECORD
